habana_quantization_toolkit/__init__.py
habana_quantization_toolkit/_core/__init__.py
habana_quantization_toolkit/_core/common.py
habana_quantization_toolkit/_core/fp_utils.py
habana_quantization_toolkit/_core/measure.py
habana_quantization_toolkit/_core/quant_dequant.py
habana_quantization_toolkit/_core/quantize.py
habana_quantization_toolkit/_core/scale.py
habana_quantization_toolkit/_core/utils.py
habana_quantization_toolkit/_core/scale_methods/__init__.py
habana_quantization_toolkit/_core/scale_methods/max_abs.py
habana_quantization_toolkit/_core/scale_methods/smooth_quant.py
habana_quantization_toolkit/_core/scale_methods/unit_scale.py
habana_quantization_toolkit/_quant_common/__init__.py
habana_quantization_toolkit/_quant_common/helper_modules.py
habana_quantization_toolkit/_quant_common/quant_config.py
habana_quantization_toolkit/prepare_quant/__init__.py
habana_quantization_toolkit/prepare_quant/prepare_model.py
habana_quantization_toolkit/scripts/__init__.py
habana_quantization_toolkit/scripts/regression_detection/__init__.py
habana_quantization_toolkit/scripts/regression_detection/regression_detection.py
habana_quantization_toolkit/utils/__init__.py
habana_quantization_toolkit/utils/logger.py
habana_quantization_toolkit-1.17.1.40.dist-info/LICENSE.txt
habana_quantization_toolkit-1.17.1.40.dist-info/METADATA
habana_quantization_toolkit-1.17.1.40.dist-info/WHEEL
habana_quantization_toolkit-1.17.1.40.dist-info/top_level.txt
habana_quantization_toolkit-1.17.1.40.dist-info/RECORD
