Metadata-Version: 2.1
Name: habana_quantization_toolkit
Version: 1.17.1.40
Summary: A tool for measurements and quantization of models in pytorch.
Author: Habana Labs Ltd., an Intel Company
Author-email: support@habana.ai
License: See LICENSE.txt
License-File: LICENSE.txt
Requires-Dist: numpy
